README.md
setup.py
overload/__init__.py
overload/overload.py
overload_python.egg-info/PKG-INFO
overload_python.egg-info/SOURCES.txt
overload_python.egg-info/dependency_links.txt
overload_python.egg-info/top_level.txt
test/test_main.py