Metadata-Version: 1.1
Name: overload-python
Version: 2.0.0
Summary: A Python implementation of the overload feature
Home-page: https://github.com/idoheinemann/python-overload
Author: Ido Heinemann
Author-email: idohaineman@gmail.com
License: Apache License 2.0
Keywords: overload,overloading,polymorphism
Platform: UNKNOWN
Classifier: Development Status :: 4 - Beta
Classifier: Intended Audience :: Developers
Classifier: Programming Language :: Python :: 3
Classifier: Programming Language :: Python :: 3.5
Classifier: Programming Language :: Python :: 3.6
Classifier: Programming Language :: Python :: 3.7
Classifier: Programming Language :: Python :: 3.8
